mm_geo_coder/__init__.py
mm_geo_coder/config.py
mm_geo_coder/database_utils.py
mm_geo_coder/geocoder.py
mm_geo_coder/geocoder_utils.py
mm_geo_coder/mimu_database.py
mm_geo_coder/nominatim.py
mm_geo_coder/database/mimu_geo_data_public.db
mm_geo_coder-0.2.1.dist-info/licenses/LICENSE
mm_geo_coder-0.2.1.dist-info/METADATA
mm_geo_coder-0.2.1.dist-info/WHEEL
mm_geo_coder-0.2.1.dist-info/top_level.txt
mm_geo_coder-0.2.1.dist-info/RECORD
