Metadata-Version: 2.4
Name: mm_geo_coder
Version: 0.2.1
Summary: A Goe_coder to locate the coordinates of addresses from Myanmar
Author-email: myothida <mmdt@istarvz.com>
License-Expression: MIT
Project-URL: Homepage, https://github.com/myothida/mm_geo_coder
Project-URL: Issues, https://github.com/myothida/mm_geo_coder/issues
Classifier: Programming Language :: Python :: 3
Classifier: Operating System :: OS Independent
Requires-Python: >=3.9
License-File: LICENSE
Requires-Dist: regex
Requires-Dist: rapidfuzz
Requires-Dist: mm_address_parser
Provides-Extra: dev
Requires-Dist: pytest; extra == "dev"
Requires-Dist: black; extra == "dev"
Requires-Dist: isort; extra == "dev"
Requires-Dist: mypy; extra == "dev"
Dynamic: license-file
